[{"day": "Sun", "date": "May 22", "condition": "Partly cloudy", "min": "17°", "max": "28°", "wind": "ESE20", "sea condition": "moderate", "probability": "High"}, {"day": "Mon", "date": "May 23", "condition": "Few afternoon showers", "min": "17°", "max": "28°", "wind": "ESE20", "sea condition": "moderate", "probability": "High"}, {"day": "Tue", "date": "May 24", "condition": "Fair day. Night passing showers", "min": "17°", "max": "28°", "wind": "ESE25G50", "sea condition": "moderate", "probability": "High"}, {"day": "Wed", "date": "May 25", "condition": "Few showers E, S & CP", "min": "17°", "max": "27°", "wind": "E25G50", "sea condition": "moderate", "probability": "Medium"}, {"day": "Thu", "date": "May 26", "condition": "Partly cloudy", "min": "18°", "max": "29°", "wind": "E15", "sea condition": "moderate", "probability": "Medium"}, {"day": "Fri", "date": "May 27", "condition": "Fine", "min": "18°", "max": "29°", "wind": "ESE10", "sea condition": "moderate", "probability": "Low"}, {"day": "Sat", "date": "May 28", "condition": "Afternoon showers Southern half & CP", "min": "16°", "max": "28°", "wind": "S20", "sea condition": "moderate", "probability": "Low"}]