[{"day": "Wed", "date": "May 25", "condition": "Fine night", "min": "17°", "max": "30°", "wind": "E10-20", "sea condition": "moderate", "probability": "High"}, {"day": "Thu", "date": "May 26", "condition": "Fair ", "min": "15°", "max": "30°", "wind": "ESE10-20", "sea condition": "moderate", "probability": "High"}, {"day": "Fri", "date": "May 27", "condition": "Fair", "min": "14°", "max": "30°", "wind": "S15", "sea condition": "moderate", "probability": "High"}, {"day": "Sat", "date": "May 28", "condition": "Morning showers", "min": "15°", "max": "28°", "wind": "S20", "sea condition": "rough", "probability": "Medium"}, {"day": "Sun", "date": "May 29", "condition": "Few showers CP", "min": "15°", "max": "27°", "wind": "SE25G50", "sea condition": "rough", "probability": "Medium"}, {"day": "Mon", "date": "May 30", "condition": "Few passing showers", "min": "15°", "max": "27°", "wind": "ESE25G50", "sea condition": "rough", "probability": "Low"}, {"day": "Tue", "date": "May 31", "condition": "Few passing showers", "min": "15°", "max": "27°", "wind": "ESE25G50", "sea condition": "rough", "probability": "Low"}]