[{"day": "Thu", "date": "Jun  2", "condition": "Occasional showers E and CP", "min": "15°", "max": "30°", "wind": "E15", "sea condition": "moderate", "probability": "High"}, {"day": "Fri", "date": "Jun  3", "condition": "Night showers E, S and CP", "min": "14°", "max": "28°", "wind": "SE20", "sea condition": "rough", "probability": "High"}, {"day": "Sat", "date": "Jun  4", "condition": "Passing showers", "min": "15°", "max": "26°", "wind": "SE25G50", "sea condition": "rough", "probability": "High"}, {"day": "Sun", "date": "Jun  5", "condition": "Passing showers", "min": "15°", "max": "26°", "wind": "ESE25G50", "sea condition": "rough", "probability": "Medium"}, {"day": "Mon", "date": "Jun  6", "condition": "Few showers E and CP", "min": "15°", "max": "28°", "wind": "E20", "sea condition": "rough", "probability": "Medium"}, {"day": "Tue", "date": "Jun  7", "condition": "Occasional showers CP", "min": "14°", "max": "28°", "wind": "ESE20", "sea condition": "rough", "probability": "Low"}, {"day": "Wed", "date": "Jun  8", "condition": "Partly cloudy", "min": "14°", "max": "27°", "wind": "SE20", "sea condition": "rough", "probability": "Low"}]