[{"day": "Wed", "date": "Mar  1", "condition": "Afternoon localised showers N, W and CP. Temporarily heavy with isol TS", "min": "19°", "max": "33°", "wind": "VRB10", "sea condition": "moderate", "probability": "High"}, {"day": "Thu", "date": "Mar  2", "condition": "Afternoon localised showers S, E and CP. Temporarily heavy with isol TS", "min": "19°", "max": "34°", "wind": "NE10", "sea condition": "moderate", "probability": "High"}, {"day": "Fri", "date": "Mar  3", "condition": "Afternoon localised showers S, SE and CP. Temporarily heavy with TS", "min": "19°", "max": "34°", "wind": "N10", "sea condition": "moderate", "probability": "High"}, {"day": "Sat", "date": "Mar  4", "condition": "Moderate showers with TS", "min": "20°", "max": "32°", "wind": "NNW10", "sea condition": "rough", "probability": "Medium"}, {"day": "Sun", "date": "Mar  5", "condition": "Moderate showers with TS", "min": "20°", "max": "31°", "wind": "N10", "sea condition": "rough", "probability": "Medium"}, {"day": "Mon", "date": "Mar  6", "condition": "Moderate showers with TS", "min": "20°", "max": "31°", "wind": "N10", "sea condition": "moderate", "probability": "Low"}, {"day": "Tue", "date": "Mar  7", "condition": "Moderate showers with TS", "min": "20°", "max": "31°", "wind": "NE10", "sea condition": "moderate", "probability": "Low"}]