[{"day": "Tue", "date": "Oct 24", "condition": "Afternoon localised showers S & SW", "min": "18°", "max": "32°", "wind": "NE15-25", "sea condition": "moderate", "probability": "High"}, {"day": "Wed", "date": "Oct 25", "condition": "Afternoon cloudy SW", "min": "18°", "max": "33°", "wind": "NE20", "sea condition": "moderate", "probability": "High"}, {"day": "Thu", "date": "Oct 26", "condition": "Few afternoon showers S & CP", "min": "18°", "max": "33°", "wind": "N15", "sea condition": "moderate", "probability": "High"}, {"day": "Fri", "date": "Oct 27", "condition": "Afternoon and night showers, locally moderate", "min": "17°", "max": "33°", "wind": "N10", "sea condition": "moderate", "probability": "Medium"}, {"day": "Sat", "date": "Oct 28", "condition": "Showers at times", "min": "16°", "max": "32°", "wind": "VRB10", "sea condition": "moderate", "probability": "Medium"}, {"day": "Sun", "date": "Oct 29", "condition": "Afternoon localised showers W & CP", "min": "17°", "max": "32°", "wind": "E10", "sea condition": "moderate", "probability": "Low"}, {"day": "Mon", "date": "Oct 30", "condition": "Afternoon localised showers W & CP", "min": "17°", "max": "32°", "wind": "ESE15", "sea condition": "moderate", "probability": "Low"}]