[{"day": "Sun", "date": "Feb 18", "condition": "Few night showers CP", "min": "18°", "max": "33°", "wind": "ESE25G50", "sea condition": "rough", "probability": "High"}, {"day": "Mon", "date": "Feb 19", "condition": "Fair day. Few night showers CP", "min": "20°", "max": "32°", "wind": "E30G55", "sea condition": "rough", "probability": "High"}, {"day": "Tue", "date": "Feb 20", "condition": "Few showers E, S & CP", "min": "20°", "max": "32°", "wind": "E35G60", "sea condition": "rough", "probability": "High"}, {"day": "Wed", "date": "Feb 21", "condition": "Windy. Passing showers", "min": "21°", "max": "31°", "wind": "E40G80", "sea condition": "rough", "probability": "Medium"}, {"day": "Thu", "date": "Feb 22", "condition": "Showery & Gusty", "min": "21°", "max": "31°", "wind": "NE50G100", "sea condition": "very rough", "probability": "Medium"}, {"day": "Fri", "date": "Feb 23", "condition": "Showery & Gusty", "min": "21°", "max": "31°", "wind": "NW60G120", "sea condition": "very rough", "probability": "Low"}, {"day": "Sat", "date": "Feb 24", "condition": "Showery & Gusty", "min": "21°", "max": "31°", "wind": "NW50G110", "sea condition": "very rough", "probability": "Low"}]