[{"day": "Tue", "date": "Sep 24", "condition": "Fine night", "min": "15°", "max": "29°", "wind": "SE20", "sea condition": "rough", "probability": "High"}, {"day": "Wed", "date": "Sep 25", "condition": "Few showers E, S & CP", "min": "15°", "max": "29°", "wind": "ESE25G50", "sea condition": "rough", "probability": "High"}, {"day": "Thu", "date": "Sep 26", "condition": "Occasional rain E, S & CP", "min": "16°", "max": "28°", "wind": "ESE25G50", "sea condition": "rough", "probability": "High"}, {"day": "Fri", "date": "Sep 27", "condition": "Intermittent rain", "min": "16°", "max": "28°", "wind": "ESE25G50", "sea condition": "rough", "probability": "Medium"}, {"day": "Sat", "date": "Sep 28", "condition": "Occasional morning rain CP", "min": "16°", "max": "29°", "wind": "E15", "sea condition": "moderate", "probability": "Medium"}, {"day": "Sun", "date": "Sep 29", "condition": "Partly cloudy", "min": "15°", "max": "30°", "wind": "E15", "sea condition": "moderate", "probability": "Low"}, {"day": "Mon", "date": "Sep 30", "condition": "Partly cloudy", "min": "15°", "max": "30°", "wind": "E20", "sea condition": "moderate", "probability": "Low"}]