[{"day": "Sat", "date": "Jun 14", "condition": "Drizzle over windward slopes", "min": "15°", "max": "28°", "wind": "SE30G70", "sea condition": "rough", "probability": "High"}, {"day": "Sun", "date": "Jun 15", "condition": "Intermittent rain E, S & CP", "min": "15°", "max": "26°", "wind": "SE30G60", "sea condition": "rough", "probability": "High"}, {"day": "Mon", "date": "Jun 16", "condition": "Cold and light rain highgrounds", "min": "15°", "max": "26°", "wind": "ESE30G60", "sea condition": "very rough", "probability": "High"}, {"day": "Tue", "date": "Jun 17", "condition": "Cold and light rain highgrounds", "min": "15°", "max": "26°", "wind": "ESE25G50", "sea condition": "rough", "probability": "Medium"}, {"day": "Wed", "date": "Jun 18", "condition": "Morning light rain CP", "min": "16°", "max": "27°", "wind": "ESE25G50", "sea condition": "rough", "probability": "Medium"}, {"day": "Thu", "date": "Jun 19", "condition": "Mainly Fair", "min": "16°", "max": "28°", "wind": "E20", "sea condition": "rough", "probability": "Low"}, {"day": "Fri", "date": "Jun 20", "condition": "Mainly Fair", "min": "16°", "max": "28°", "wind": "E20", "sea condition": "rough", "probability": "Low"}]