[{"day": "Sat", "date": "Jun 27", "condition": "Showers E, S & CP mod at times", "min": "15°", "max": "28°", "wind": "SE25G50", "sea condition": "rough", "probability": "High"}, {"day": "Sun", "date": "Jun 28", "condition": "Afternoon and night showers E, S, CP", "min": "16°", "max": "28°", "wind": "SE25G50", "sea condition": "rough", "probability": "High"}, {"day": "Mon", "date": "Jun 29", "condition": "Partly cloudy", "min": "15°", "max": "29°", "wind": "SE20", "sea condition": "rough", "probability": "High"}, {"day": "Tue", "date": "Jun 30", "condition": "Few morning showers", "min": "15°", "max": "29°", "wind": "SE15", "sea condition": "rough", "probability": "Medium"}, {"day": "Wed", "date": "Jul  1", "condition": "Partly cloudy", "min": "15°", "max": "29°", "wind": "ESE15", "sea condition": "rough", "probability": "Medium"}, {"day": "Thu", "date": "Jul  2", "condition": "Partly cloudy", "min": "15°", "max": "29°", "wind": "ESE20", "sea condition": "rough", "probability": "Low"}, {"day": "Fri", "date": "Jul  3", "condition": "Partly cloudy", "min": "15°", "max": "29°", "wind": "ESE20", "sea condition": "rough", "probability": "Low"}]