[{"day": "Sat", "date": "Jun 20", "condition": "Night intermittent rain", "min": "12°", "max": "29°", "wind": "VRB10", "sea condition": "moderate", "probability": "High"}, {"day": "Sun", "date": "Jun 21", "condition": "Morning intermittent rain", "min": "15°", "max": "26°", "wind": "S25G60", "sea condition": "very rough", "probability": "High"}, {"day": "Mon", "date": "Jun 22", "condition": "Light rain CP", "min": "14°", "max": "26°", "wind": "SSE25G50", "sea condition": "very rough", "probability": "High"}, {"day": "Tue", "date": "Jun 23", "condition": "Light rain CP", "min": "15°", "max": "27°", "wind": "SE25G50", "sea condition": "rough", "probability": "Medium"}, {"day": "Wed", "date": "Jun 24", "condition": "Light rain", "min": "15°", "max": "27°", "wind": "ESE25G50", "sea condition": "rough", "probability": "Medium"}, {"day": "Thu", "date": "Jun 25", "condition": "Light rain", "min": "15°", "max": "27°", "wind": "ESE25G50", "sea condition": "rough", "probability": "Low"}, {"day": "Fri", "date": "Jun 26", "condition": "Intermittent rain", "min": "15°", "max": "27°", "wind": "ESE25G50", "sea condition": "rough", "probability": "Low"}]